video_stream/__init__.py
video_stream/log.py
video_stream/stream.py
pyStreamRead-3.0.3.dist-info/METADATA
pyStreamRead-3.0.3.dist-info/WHEEL
pyStreamRead-3.0.3.dist-info/top_level.txt
pyStreamRead-3.0.3.dist-info/RECORD
