Metadata-Version: 2.1
Name: pyStreamRead
Version: 3.0.3
Summary: video stream reading
Author: rui.li
Author-email: jiangsulirui@gmail.com
License: MIT Licence
Keywords: rtsp,rtmp,video,stream,python,video_stream
Platform: any
Requires-Python: >=3.12
Requires-Dist: ffmpeg-python ==0.2.0
Requires-Dist: future ==1.0.0
Requires-Dist: numpy ==2.1.2
Requires-Dist: opencv-python ==4.10.0.84
